numerous/__init__.py
numerous/__main__.py
numerous/py.typed
numerous/_cli/__init__.py
numerous/_cli/__main__.py
numerous/_cli/color.py
numerous/_cli/run.py
numerous/_cli/upgrade.py
numerous/_cli/bin/cli
numerous/_client/__init__.py
numerous/_client/exceptions.py
numerous/_client/factory.py
numerous/_client/fs_client.py
numerous/_client/graphql_client.py
numerous/_client/threaded_event_loop.py
numerous/_client/graphql/__init__.py
numerous/_client/graphql/async_base_client.py
numerous/_client/graphql/base_model.py
numerous/_client/graphql/client.py
numerous/_client/graphql/collection_collections.py
numerous/_client/graphql/collection_create.py
numerous/_client/graphql/collection_document.py
numerous/_client/graphql/collection_document_delete.py
numerous/_client/graphql/collection_document_in_collection.py
numerous/_client/graphql/collection_document_set.py
numerous/_client/graphql/collection_document_tag_add.py
numerous/_client/graphql/collection_document_tag_delete.py
numerous/_client/graphql/collection_documents.py
numerous/_client/graphql/collection_file.py
numerous/_client/graphql/collection_file_create.py
numerous/_client/graphql/collection_file_delete.py
numerous/_client/graphql/collection_file_tag_add.py
numerous/_client/graphql/collection_file_tag_delete.py
numerous/_client/graphql/collection_files.py
numerous/_client/graphql/collection_tag_add.py
numerous/_client/graphql/collection_tag_delete.py
numerous/_client/graphql/collection_tags.py
numerous/_client/graphql/enums.py
numerous/_client/graphql/exceptions.py
numerous/_client/graphql/fragments.py
numerous/_client/graphql/input_types.py
numerous/_client/graphql/organization_by_id.py
numerous/_utils/__init__.py
numerous/_utils/jsonbase64.py
numerous/_utils/local.py
numerous/collections/__init__.py
numerous/collections/_client.py
numerous/collections/_get_client.py
numerous/collections/collection.py
numerous/collections/collection_reference.py
numerous/collections/document_reference.py
numerous-0.50.0.dist-info/METADATA
numerous-0.50.0.dist-info/WHEEL
numerous-0.50.0.dist-info/entry_points.txt
numerous-0.50.0.dist-info/top_level.txt
numerous-0.50.0.dist-info/RECORD
