Metadata-Version: 2.4
Name: numerous
Version: 0.50.0
Classifier: Programming Language :: Python :: 3
Requires-Dist: typing-extensions>=4.12.2
Requires-Dist: requests>=2.32.3
Requires-Dist: httpx<0.28.0,>=0.23
Requires-Dist: pydantic<2.10.0,>=2.9.0
Requires-Dist: websockets>=0.11
Requires-Dist: pathspec
Provides-Extra: dev
Requires-Dist: pre-commit; extra == "dev"
Requires-Dist: pytest==8.3.2; extra == "dev"
Requires-Dist: pytest-asyncio==0.24.0; extra == "dev"
Requires-Dist: freezegun==1.4.0; extra == "dev"
Requires-Dist: ruff==0.6.4; extra == "dev"
Requires-Dist: mypy==1.11.2; extra == "dev"
Requires-Dist: types-requests>=2.32.0; extra == "dev"
Requires-Dist: coverage==7.6.1; extra == "dev"
Requires-Dist: twine==5.1.1; extra == "dev"
Requires-Dist: marimo==0.8.14; extra == "dev"
Requires-Dist: types-setuptools>=74.1.0; extra == "dev"
Requires-Dist: build==1.2.2; extra == "dev"
Requires-Dist: ariadne-codegen[subscriptions]>=0.14.0; extra == "dev"
Requires-Dist: mkdocs==1.6.0; extra == "dev"
Requires-Dist: mkdocstrings==0.26.2; extra == "dev"
Requires-Dist: mkdocstrings-python==1.12.2; extra == "dev"
Requires-Dist: mkdocs_snippet_plugin==1.0.2; extra == "dev"
Requires-Dist: mkdocs-material==9.5.46; extra == "dev"
Requires-Dist: mkdocs-gen-files==0.5.0; extra == "dev"
Requires-Dist: mkdocs-section-index==0.3.9; extra == "dev"
Requires-Dist: mkdocs-literate-nav==0.6.1; extra == "dev"
Requires-Dist: flask; extra == "dev"
Requires-Dist: fastapi; extra == "dev"
Requires-Dist: marimo; extra == "dev"
Requires-Dist: streamlit; extra == "dev"
Requires-Dist: dash; extra == "dev"
Requires-Dist: panel; extra == "dev"
